rethge_torch/__init__.py
rethge_torch/main.py
rethge_torch/rethge.py
rethge_torch/rethge_components.py
rethge_torch/rethge_train_with_track.py
rethge_torch-0.0.2.dist-info/LICENSE
rethge_torch-0.0.2.dist-info/METADATA
rethge_torch-0.0.2.dist-info/WHEEL
rethge_torch-0.0.2.dist-info/top_level.txt
rethge_torch-0.0.2.dist-info/RECORD
