Metadata-Version: 2.1
Name: rethge-torch
Version: 0.0.2
Summary: A small package that contains help functions to convenient pytorch using. including plot, model train & evaluate, results analysis and more...
Home-page: https://github.com/ReThGe/rethge_torch
Author: ReThGe
Author-email: YanShumai8274@163.com
Project-URL: Bug Tracker, https://github.com/ReThGe/rethge_torch
Classifier: Programming Language :: Python :: 3
Classifier: License :: OSI Approved :: MIT License
Classifier: Operating System :: OS Independent
Requires-Python: >=3.9
License-File: LICENSE
